{
  "data": [
    {
      "id": 1,
      "title": "Stothras",
      "dataUrl": "https://jayanthbm.github.io/stothram-data/stothras-data.json",
      "icon": "database",
      "icon_new": "book-open-page-variant-outline",
      "darkBackground": "#878683",
      "lightBackground": "#1abc9c"
    },
    {
      "id": 2,
      "title": "Bhajanas",
      "dataUrl": "https://jayanthbm.github.io/stothram-data/bhajanas-data.json",
      "icon": "profile",
      "icon_new": "book-music-outline",
      "darkBackground": "#878683",
      "lightBackground": "#3498db"
    },
    {
      "id": 3,
      "title": "Shattumorai",
      "dataUrl": "https://jayanthbm.github.io/stothram-data/shattumorai-data.json",
      "icon": "database",
      "icon_new": "stack-exchange",
      "darkBackground": "#878683",
      "lightBackground": "#1abc9c"
    }
  ],
  "UPI_ID": "EZE0223420@CUB",
  "upi_data": {
    "upi_amounts": [1, 5, 10, 50],
    "payee_name": "Stothram",
    "transaction_note": "Contribute to Stothram"
  }
}
